CHANGES.txt
CONTRIBUTORS.txt
MANIFEST.in
README.rst
setup.cfg
setup.py
tox.ini
genaa/__init__.py
genaa/block.py
genaa/box.py
genaa/compat.py
genaa/multiwidth.py
genaa/utils.py
genaa.egg-info/PKG-INFO
genaa.egg-info/SOURCES.txt
genaa.egg-info/dependency_links.txt
genaa.egg-info/entry_points.txt
genaa.egg-info/top_level.txt
genaa/commands/__init__.py
genaa/commands/block.py
genaa/commands/box.py
genaa/commands/main.py
tests/__init__.py
tests/test_block.py
tests/test_box.py
tests/test_commands.py
tests/test_multiwidth.py
tests/test_utils.py