Metadata-Version: 1.1
Name: genaa
Version: 0.4
Summary: genaa, a ASCII Art generator.
Home-page: https://github.com/hirokiky/genaa
Author: hirokiky
Author-email: hirokiky@gmail.com
License: MIT
Platform: UNKNOWN
Classifier: Programming Language :: Python :: 2
Classifier: Programming Language :: Python :: 2.7
Classifier: Programming Language :: Python :: 3
Classifier: Programming Language :: Python :: 3.3
Classifier: Development Status :: 3 - Alpha
Classifier: Topic :: Text Processing :: Filters
Classifier: License :: OSI Approved :: MIT License
